{
	"version": "6",
	"dialect": "sqlite",
	"id": "47f93726-891f-496a-9a72-8ad84b76c41b",
	"prevId": "00000000-0000-0000-0000-000000000000",
	"tables": {
		"chapters": {
			"name": "chapters",
			"columns": {
				"video_id": {
					"name": "video_id",
					"type": "text",
					"primaryKey": false,
					"notNull": true,
					"autoincrement": false
				},
				"seconds": {
					"name": "seconds",
					"type": "integer",
					"primaryKey": false,
					"notNull": true,
					"autoincrement": false
				},
				"title": {
					"name": "title",
					"type": "text",
					"primaryKey": false,
					"notNull": true,
					"autoincrement": false
				}
			},
			"indexes": {},
			"foreignKeys": {},
			"compositePrimaryKeys": {
				"chapters_video_id_seconds_pk": {
					"columns": [
						"video_id",
						"seconds"
					],
					"name": "chapters_video_id_seconds_pk"
				}
			},
			"uniqueConstraints": {},
			"checkConstraints": {}
		}
	},
	"views": {},
	"enums": {},
	"_meta": {
		"schemas": {},
		"tables": {},
		"columns": {}
	},
	"internal": {
		"indexes": {}
	}
}
