{
	"version": "6",
	"dialect": "sqlite",
	"id": "56f3f95d-20f5-4c67-a9f6-4205cf896a1e",
	"prevId": "00000000-0000-0000-0000-000000000000",
	"tables": {
		"rooms": {
			"name": "rooms",
			"columns": {
				"id": {
					"name": "id",
					"type": "text",
					"primaryKey": true,
					"notNull": true,
					"autoincrement": false
				},
				"name": {
					"name": "name",
					"type": "text",
					"primaryKey": false,
					"notNull": true,
					"autoincrement": false
				},
				"started_at": {
					"name": "started_at",
					"type": "integer",
					"primaryKey": false,
					"notNull": true,
					"autoincrement": false
				},
				"participants_joined": {
					"name": "participants_joined",
					"type": "integer",
					"primaryKey": false,
					"notNull": false,
					"autoincrement": false,
					"default": 0
				},
				"participants_left": {
					"name": "participants_left",
					"type": "integer",
					"primaryKey": false,
					"notNull": false,
					"autoincrement": false,
					"default": 0
				},
				"finished_at": {
					"name": "finished_at",
					"type": "integer",
					"primaryKey": false,
					"notNull": false,
					"autoincrement": false
				}
			},
			"indexes": {},
			"foreignKeys": {},
			"compositePrimaryKeys": {},
			"uniqueConstraints": {},
			"checkConstraints": {}
		}
	},
	"views": {},
	"enums": {},
	"_meta": {
		"schemas": {},
		"tables": {},
		"columns": {}
	},
	"internal": {
		"indexes": {}
	}
}
